setup.py
simpleFlux/__init__.py
simpleFlux.egg-info/PKG-INFO
simpleFlux.egg-info/SOURCES.txt
simpleFlux.egg-info/dependency_links.txt
simpleFlux.egg-info/entry_points.txt
simpleFlux.egg-info/requires.txt
simpleFlux.egg-info/top_level.txt
simpleFlux.egg-info/zip-safe
simpleFlux/r1_4_1_dev/__init__.py
simpleFlux/r1_5/__init__.py
simpleFlux/r1_6/__init__.py
simpleFlux/r1_7_0/__init__.py
simpleFlux/r1_7_1/__init__.py
simpleFlux/r2_0_0/__init__.py
simpleFlux/r2_1_0/__init__.py
simpleFlux/r2_1_1/__init__.py